flask_restful_arrayarg/__init__.py
flask_restful_arrayarg/array.py
flask_restful_arrayarg/nest.py
flask_restful_arrayarg/recipe/__init__.py
flask_restful_arrayarg/recipe/datatables.py
flask_restful_arrayarg/scalar.py
flask_restful_arrayarg/util.py
flask_restful_arrayarg-0.2.0.dist-info/WHEEL
flask_restful_arrayarg-0.2.0.dist-info/METADATA
flask_restful_arrayarg-0.2.0.dist-info/RECORD
