Metadata-Version: 2.1
Name: flask-restful-arrayarg
Version: 0.2.0
Summary: An extension to flask-restful argparse for PHP style array forms
Author: genzj
Author-email: zj0512@gmail.com
Requires-Python: >=2.7, !=3.0.*, !=3.1.*, !=3.2.*, !=3.3.*
Classifier: Programming Language :: Python :: 2
Classifier: Programming Language :: Python :: 2.7
Classifier: Programming Language :: Python :: 3
Classifier: Programming Language :: Python :: 3.4
Classifier: Programming Language :: Python :: 3.5
Classifier: Programming Language :: Python :: 3.6
Classifier: Programming Language :: Python :: 3.7
Requires-Dist: flask-restful (>=0.3.7,<0.4.0)
